PDC_Utils/__init__.py
PDC_Utils/_modidx.py
PDC_Utils/core.py
PDC_Utils/pdc.py
PDC_Utils-0.0.1.dist-info/LICENSE
PDC_Utils-0.0.1.dist-info/METADATA
PDC_Utils-0.0.1.dist-info/WHEEL
PDC_Utils-0.0.1.dist-info/entry_points.txt
PDC_Utils-0.0.1.dist-info/top_level.txt
PDC_Utils-0.0.1.dist-info/RECORD
