Metadata-Version: 2.1
Name: PDC-Utils
Version: 0.0.1
Summary: Utilities to manage power duration curves
Home-page: https://github.com/jpequegn/PDC-Utils
Author: Julien P
Author-email: julien.pequegnot@gmail.com
License: Apache Software License 2.0
Keywords: nbdev jupyter notebook python
Platform: UNKNOWN
Classifier: Development Status :: 4 - Beta
Classifier: Intended Audience :: Developers
Classifier: Natural Language :: English
Classifier: Programming Language :: Python :: 3.7
Classifier: Programming Language :: Python :: 3.8
Classifier: Programming Language :: Python :: 3.9
Classifier: Programming Language :: Python :: 3.10
Classifier: License :: OSI Approved :: Apache Software License
Requires-Python: >=3.7
License-File: LICENSE
Requires-Dist: fastcore
Requires-Dist: pandas
Requires-Dist: lmfit
Requires-Dist: numpy
Provides-Extra: dev
